LICENSE
MANIFEST.in
README.md
pyproject.toml
setup.py
algorithms/kmeans/elkan_commons.c
algorithms/kmeans/elkan_commons.h
algorithms/kmeans/elkan_kmeans.c
algorithms/kmeans/elkan_kmeans.h
algorithms/kmeans/init_params.c
algorithms/kmeans/init_params.h
algorithms/kmeans/kmeans.c
algorithms/kmeans/kmeans.h
algorithms/kmeans/kmeans_cluster_hashmap.c
algorithms/kmeans/kmeans_cluster_hashmap.h
algorithms/kmeans/kmeans_control.c
algorithms/kmeans/kmeans_control.h
algorithms/kmeans/kmeans_utils.c
algorithms/kmeans/kmeans_utils.h
algorithms/kmeans/kmeanspp.c
algorithms/kmeans/kmeanspp.h
algorithms/kmeans/minibatch_commons.c
algorithms/kmeans/minibatch_commons.h
algorithms/kmeans/minibatch_kmeans.c
algorithms/kmeans/minibatch_kmeans.h
algorithms/kmeans/nc_kmeans.c
algorithms/kmeans/nc_kmeans.h
algorithms/kmeans/pca_elkan_kmeans.c
algorithms/kmeans/pca_elkan_kmeans.h
algorithms/kmeans/pca_kmeans.c
algorithms/kmeans/pca_kmeans.h
algorithms/kmeans/pca_minibatch_kmeans.c
algorithms/kmeans/pca_minibatch_kmeans.h
algorithms/kmeans/pca_yinyang.c
algorithms/kmeans/pca_yinyang.h
algorithms/kmeans/yinyang.c
algorithms/kmeans/yinyang.h
python/fcl/__init__.py
python/fcl/exceptions.py
python/fcl.egg-info/PKG-INFO
python/fcl.egg-info/SOURCES.txt
python/fcl.egg-info/dependency_links.txt
python/fcl.egg-info/top_level.txt
python/fcl/cython/__init__.py
python/fcl/cython/utils/__init__.py
python/fcl/cython/utils/cdict.pxd
python/fcl/cython/utils/cdict.pyx
python/fcl/cython/utils/global_defs.pxd
python/fcl/cython/utils/signals.pxi
python/fcl/cython/utils/types.pxd
python/fcl/cython/utils/matrix/__init__.py
python/fcl/cython/utils/matrix/csr_matrix/__init__.py
python/fcl/cython/utils/matrix/csr_matrix/csr_assign.pxd
python/fcl/cython/utils/matrix/csr_matrix/csr_assign.pyx
python/fcl/datasets/__init__.py
python/fcl/datasets/dataset_utils.py
python/fcl/kmeans/__init__.py
python/fcl/kmeans/_kmeans.pyx
python/fcl/kmeans/kmeans.py
python/fcl/matrix/__init__.py
python/fcl/matrix/csr_matrix.pxd
python/fcl/matrix/csr_matrix.pyx
python/utils/create_pca_vectors_from_dataset.py
utils/argtable3.h
utils/cdict.c
utils/cdict.h
